MANIFEST.in
README.md
requirements.txt
setup.cfg
setup.py
jsonfeed/__init__.py
jsonfeed.egg-info/PKG-INFO
jsonfeed.egg-info/SOURCES.txt
jsonfeed.egg-info/dependency_links.txt
jsonfeed.egg-info/requires.txt
jsonfeed.egg-info/top_level.txt