Metadata-Version: 1.1
Name: jsonfeed
Version: 0.0.1
Summary: A python package to process json feed http://jsonfeed.org/
Home-page: https://github.com/jibaku/jsonfeed
Author: Fabien Schwob
Author-email: xphuture@gmail.com
License: BSD
Download-URL: https://github.com/jibaku/jsonfeed/tarball/0.0.1
Platform: UNKNOWN
Classifier: Development Status :: 3 - Alpha
Classifier: Intended Audience :: Developers
Classifier: Programming Language :: Python :: 3
